{
  "info": {
    "description": "data",
    "version": "1.0",
    "year": 2025,
    "contributor": "search engine",
    "source": "augmented",
    "license": {
      "name": "Creative Commons Attribution 4.0 International",
      "url": "https://creativecommons.org/licenses/by/4.0/"
    }
  },
  "images": [
    {
      "id": 1501655696,
      "width": 640,
      "height": 640,
      "file_name": "IMGP9472_3.jpg",
      "size": 44282,
      "format": "JPEG",
      "url": "",
      "hash": "",
      "status": "success"
    }
  ],
  "annotations": [
    {
      "id": 7604542696,
      "image_id": 1501655696,
      "category_id": 9697349696,
      "segmentation": [],
      "area": 1088.5111615488001,
      "bbox": [
        340.37728000000004,
        244.52832,
        36.981120000000004,
        29.43424
      ]
    },
    {
      "id": 9987120696,
      "image_id": 1501655696,
      "category_id": 9697349696,
      "segmentation": [],
      "area": 1151.17707264,
      "bbox": [
        409.05664,
        238.49055999999996,
        32.45312,
        35.472
      ]
    },
    {
      "id": 2577723696,
      "image_id": 1501655696,
      "category_id": 9697349696,
      "segmentation": [],
      "area": 1753.2155260927998,
      "bbox": [
        446.79263999999995,
        299.62272,
        40.75456,
        43.018879999999996
      ]
    },
    {
      "id": 8251869696,
      "image_id": 1501655696,
      "category_id": 9697349696,
      "segmentation": [],
      "area": 1281.5882207232,
      "bbox": [
        560.75456,
        254.33984000000004,
        33.96224,
        37.73568
      ]
    },
    {
      "id": 7412131696,
      "image_id": 1501655696,
      "category_id": 9697349696,
      "segmentation": [],
      "area": 1050.9058187264002,
      "bbox": [
        569.05632,
        302.64128,
        30.943360000000002,
        33.96224
      ]
    },
    {
      "id": 1814240696,
      "image_id": 1501655696,
      "category_id": 9697349696,
      "segmentation": [],
      "area": 350.50153164799997,
      "bbox": [
        627.5648,
        403.73088,
        12.4352,
        28.186239999999998
      ]
    },
    {
      "id": 9610860696,
      "image_id": 1501655696,
      "category_id": 9697349696,
      "segmentation": [],
      "area": 537.4416949248,
      "bbox": [
        3.316159999999999,
        320.00032,
        19.067520000000002,
        28.186239999999998
      ]
    },
    {
      "id": 1588144696,
      "image_id": 1501655696,
      "category_id": 9697349696,
      "segmentation": [],
      "area": 556.683116544,
      "bbox": [
        10.776960000000003,
        300.93248,
        22.38336,
        24.8704
      ]
    },
    {
      "id": 2734170696,
      "image_id": 1501655696,
      "category_id": 9697349696,
      "segmentation": [],
      "area": 1033.6576843776,
      "bbox": [
        71.29503999999999,
        48.08288,
        26.528640000000003,
        38.96384
      ]
    }
  ],
  "categories": [
    {
      "id": 9697349696,
      "name": "AppleBBCH81",
      "supercategory": "apple"
    }
  ]
}