{
  "info": {
    "description": "data",
    "version": "1.0",
    "year": 2025,
    "contributor": "search engine",
    "source": "augmented",
    "license": {
      "name": "Creative Commons Attribution 4.0 International",
      "url": "https://creativecommons.org/licenses/by/4.0/"
    }
  },
  "images": [
    {
      "id": 1278647693,
      "width": 640,
      "height": 640,
      "file_name": "IMGP9453_2.jpg",
      "size": 40593,
      "format": "JPEG",
      "url": "",
      "hash": "",
      "status": "success"
    }
  ],
  "annotations": [
    {
      "id": 2430648693,
      "image_id": 1278647693,
      "category_id": 8044189693,
      "segmentation": [],
      "area": 1948.032546816,
      "bbox": [
        461.88703999999996,
        238.49056000000002,
        43.018879999999996,
        45.2832
      ]
    },
    {
      "id": 5035928693,
      "image_id": 1278647693,
      "category_id": 8044189693,
      "segmentation": [],
      "area": 371.12685281280005,
      "bbox": [
        210.56992000000002,
        213.88608000000002,
        16.58048,
        22.38336
      ]
    }
  ],
  "categories": [
    {
      "id": 8044189693,
      "name": "AppleBBCH81",
      "supercategory": "apple"
    }
  ]
}