{
  "info": {
    "description": "data",
    "version": "1.0",
    "year": 2025,
    "contributor": "search engine",
    "source": "augmented",
    "license": {
      "name": "Creative Commons Attribution 4.0 International",
      "url": "https://creativecommons.org/licenses/by/4.0/"
    }
  },
  "images": [
    {
      "id": 8514624689,
      "width": 640,
      "height": 640,
      "file_name": "IMGP9419_15.jpg",
      "size": 52101,
      "format": "JPEG",
      "url": "",
      "hash": "",
      "status": "success"
    }
  ],
  "annotations": [
    {
      "id": 6469789689,
      "image_id": 8514624689,
      "category_id": 4044389689,
      "segmentation": [],
      "area": 1133.7234599935998,
      "bbox": [
        240.41439999999997,
        111.08832000000001,
        32.79296,
        34.57216
      ]
    },
    {
      "id": 1421118689,
      "image_id": 8514624689,
      "category_id": 4044389689,
      "segmentation": [],
      "area": 1193.4241521664003,
      "bbox": [
        303.39648,
        152.53888,
        31.697920000000003,
        37.64992
      ]
    },
    {
      "id": 1497614689,
      "image_id": 8514624689,
      "category_id": 4044389689,
      "segmentation": [],
      "area": 948.41778176,
      "bbox": [
        254.50784,
        273.57504,
        38.1344,
        24.8704
      ]
    },
    {
      "id": 7801166689,
      "image_id": 8514624689,
      "category_id": 4044389689,
      "segmentation": [],
      "area": 1480.9533652992002,
      "bbox": [
        166.03776,
        319.99968,
        37.73568,
        39.24544
      ]
    },
    {
      "id": 4994426689,
      "image_id": 8514624689,
      "category_id": 4044389689,
      "segmentation": [],
      "area": 747.7426139136,
      "bbox": [
        255.33664,
        389.63743999999997,
        26.528640000000003,
        28.186239999999998
      ]
    },
    {
      "id": 7845460689,
      "image_id": 8514624689,
      "category_id": 4044389689,
      "segmentation": [],
      "area": 827.2618131456002,
      "bbox": [
        190.67360000000002,
        612.64224,
        33.989760000000004,
        24.33856
      ]
    },
    {
      "id": 2923381689,
      "image_id": 8514624689,
      "category_id": 4044389689,
      "segmentation": [],
      "area": 470.500608,
      "bbox": [
        504.15072,
        549.63744,
        35.472,
        13.264
      ]
    },
    {
      "id": 4760760689,
      "image_id": 8514624689,
      "category_id": 4044389689,
      "segmentation": [],
      "area": 579.333087232,
      "bbox": [
        376.37312000000003,
        581.8870400000001,
        24.8704,
        23.29408
      ]
    },
    {
      "id": 8827913689,
      "image_id": 8514624689,
      "category_id": 4044389689,
      "segmentation": [],
      "area": 676.8584810496,
      "bbox": [
        462.5904,
        281.8656,
        30.239359999999998,
        22.38336
      ]
    }
  ],
  "categories": [
    {
      "id": 4044389689,
      "name": "AppleBBCH81",
      "supercategory": "apple"
    }
  ]
}