{
  "info": {
    "description": "data",
    "version": "1.0",
    "year": 2025,
    "contributor": "search engine",
    "source": "augmented",
    "license": {
      "name": "Creative Commons Attribution 4.0 International",
      "url": "https://creativecommons.org/licenses/by/4.0/"
    }
  },
  "images": [
    {
      "id": 2724176679,
      "width": 640,
      "height": 640,
      "file_name": "IMGP9356_4.jpg",
      "size": 49002,
      "format": "JPEG",
      "url": "",
      "hash": "",
      "status": "success"
    }
  ],
  "annotations": [
    {
      "id": 6565277679,
      "image_id": 2724176679,
      "category_id": 1693871679,
      "segmentation": [],
      "area": 974.2540181504,
      "bbox": [
        210.20448,
        207.34688000000003,
        27.75488,
        35.10208
      ]
    },
    {
      "id": 6212713679,
      "image_id": 2724176679,
      "category_id": 1693871679,
      "segmentation": [],
      "area": 830.8867469312002,
      "bbox": [
        26.47904,
        317.55104000000006,
        26.174080000000004,
        31.74464
      ]
    },
    {
      "id": 1107810679,
      "image_id": 2724176679,
      "category_id": 1693871679,
      "segmentation": [],
      "area": 617.845690368,
      "bbox": [
        49.38752000000001,
        297.95936,
        26.668799999999997,
        23.167360000000002
      ]
    },
    {
      "id": 4130210679,
      "image_id": 2724176679,
      "category_id": 1693871679,
      "segmentation": [],
      "area": 785.0036137983999,
      "bbox": [
        191.42879999999997,
        154.28575999999998,
        25.30624,
        31.020159999999997
      ]
    },
    {
      "id": 2713743679,
      "image_id": 2724176679,
      "category_id": 1693871679,
      "segmentation": [],
      "area": 490.4628191231999,
      "bbox": [
        210.20416,
        125.71424,
        26.122239999999998,
        18.775679999999998
      ]
    },
    {
      "id": 1445864679,
      "image_id": 2724176679,
      "category_id": 1693871679,
      "segmentation": [],
      "area": 557.7738235904,
      "bbox": [
        219.99967999999998,
        270.20384,
        22.04096,
        25.30624
      ]
    },
    {
      "id": 5155945679,
      "image_id": 2724176679,
      "category_id": 1693871679,
      "segmentation": [],
      "area": 543.7647273984,
      "bbox": [
        215.1024,
        142.85696000000002,
        27.75488,
        19.59168
      ]
    },
    {
      "id": 9423790679,
      "image_id": 2724176679,
      "category_id": 1693871679,
      "segmentation": [],
      "area": 1070.7698921472002,
      "bbox": [
        274.40416,
        164.97376000000003,
        31.502720000000004,
        33.989760000000004
      ]
    },
    {
      "id": 6281287679,
      "image_id": 2724176679,
      "category_id": 1693871679,
      "segmentation": [],
      "area": 518.2061096960001,
      "bbox": [
        282.69408,
        150.88096,
        21.554560000000002,
        24.041600000000003
      ]
    },
    {
      "id": 8345367679,
      "image_id": 2724176679,
      "category_id": 1693871679,
      "segmentation": [],
      "area": 584.1632063487999,
      "bbox": [
        261.14016,
        145.07808,
        28.186239999999998,
        20.72512
      ]
    },
    {
      "id": 5014577679,
      "image_id": 2724176679,
      "category_id": 1693871679,
      "segmentation": [],
      "area": 661.1490541568,
      "bbox": [
        421.96896000000004,
        243.73088,
        21.554560000000002,
        30.67328
      ]
    }
  ],
  "categories": [
    {
      "id": 1693871679,
      "name": "AppleBBCH81",
      "supercategory": "apple"
    }
  ]
}