{
  "info": {
    "description": "data",
    "version": "1.0",
    "year": 2025,
    "contributor": "search engine",
    "source": "augmented",
    "license": {
      "name": "Creative Commons Attribution 4.0 International",
      "url": "https://creativecommons.org/licenses/by/4.0/"
    }
  },
  "images": [
    {
      "id": 4985379693,
      "width": 640,
      "height": 640,
      "file_name": "IMGP9448_2.jpg",
      "size": 61584,
      "format": "JPEG",
      "url": "",
      "hash": "",
      "status": "success"
    }
  ],
  "annotations": [
    {
      "id": 1279641693,
      "image_id": 4985379693,
      "category_id": 7871219693,
      "segmentation": [],
      "area": 191.75467417599998,
      "bbox": [
        192.56575999999998,
        246.06399999999996,
        13.702399999999999,
        13.99424
      ]
    },
    {
      "id": 5747503693,
      "image_id": 4985379693,
      "category_id": 7871219693,
      "segmentation": [],
      "area": 187.4158301184,
      "bbox": [
        211.22463999999997,
        268.51295999999996,
        14.285440000000001,
        13.11936
      ]
    },
    {
      "id": 8065024693,
      "image_id": 4985379693,
      "category_id": 7871219693,
      "segmentation": [],
      "area": 146.19956674559998,
      "bbox": [
        239.21280000000002,
        253.06112,
        11.66208,
        12.53632
      ]
    },
    {
      "id": 9408972693,
      "image_id": 4985379693,
      "category_id": 7871219693,
      "segmentation": [],
      "area": 97.9141521408,
      "bbox": [
        247.37632000000002,
        228.57183999999995,
        9.32928,
        10.49536
      ]
    },
    {
      "id": 4857874693,
      "image_id": 4985379693,
      "category_id": 7871219693,
      "segmentation": [],
      "area": 179.5203497984,
      "bbox": [
        274.1984,
        243.44,
        13.99424,
        12.82816
      ]
    },
    {
      "id": 6682757693,
      "image_id": 4985379693,
      "category_id": 7871219693,
      "segmentation": [],
      "area": 160.6481375232,
      "bbox": [
        305.97664000000003,
        295.91839999999996,
        12.24512,
        13.11936
      ]
    },
    {
      "id": 4933391693,
      "image_id": 4985379693,
      "category_id": 7871219693,
      "segmentation": [],
      "area": 206.5428074496,
      "bbox": [
        436.29728,
        296.79328,
        15.74336,
        13.11936
      ]
    },
    {
      "id": 1610505693,
      "image_id": 4985379693,
      "category_id": 7871219693,
      "segmentation": [],
      "area": 164.5616889856,
      "bbox": [
        461.37024,
        343.44,
        12.82816,
        12.82816
      ]
    },
    {
      "id": 2509816693,
      "image_id": 4985379693,
      "category_id": 7871219693,
      "segmentation": [],
      "area": 198.6424758272,
      "bbox": [
        354.95647999999994,
        392.12800000000004,
        11.95328,
        16.61824
      ]
    },
    {
      "id": 4625681693,
      "image_id": 4985379693,
      "category_id": 7871219693,
      "segmentation": [],
      "area": 129.5856451584,
      "bbox": [
        524.81216,
        348.87231999999995,
        11.60064,
        11.17056
      ]
    },
    {
      "id": 1340717693,
      "image_id": 4985379693,
      "category_id": 7871219693,
      "segmentation": [],
      "area": 148.7811354624,
      "bbox": [
        550.59104,
        365.19872,
        13.31904,
        11.17056
      ]
    },
    {
      "id": 2653870693,
      "image_id": 4985379693,
      "category_id": 7871219693,
      "segmentation": [],
      "area": 203.419107328,
      "bbox": [
        511.06368000000003,
        378.08831999999995,
        16.3264,
        12.45952
      ]
    },
    {
      "id": 2772209693,
      "image_id": 4985379693,
      "category_id": 7871219693,
      "segmentation": [],
      "area": 155.0612692992,
      "bbox": [
        551.02016,
        441.67552,
        10.31168,
        15.03744
      ]
    },
    {
      "id": 2920222693,
      "image_id": 4985379693,
      "category_id": 7871219693,
      "segmentation": [],
      "area": 217.45197465599998,
      "bbox": [
        514.93024,
        443.39456000000007,
        13.31904,
        16.3264
      ]
    },
    {
      "id": 8057765693,
      "image_id": 4985379693,
      "category_id": 7871219693,
      "segmentation": [],
      "area": 159.4961166336,
      "bbox": [
        526.53056,
        451.98720000000003,
        15.467519999999999,
        10.31168
      ]
    },
    {
      "id": 4333158693,
      "image_id": 4985379693,
      "category_id": 7871219693,
      "segmentation": [],
      "area": 158.3824551936,
      "bbox": [
        498.17408,
        472.60992,
        11.17056,
        14.178560000000001
      ]
    },
    {
      "id": 1170279693,
      "image_id": 4985379693,
      "category_id": 7871219693,
      "segmentation": [],
      "area": 353.7290526720001,
      "bbox": [
        398.49055999999996,
        390.18879999999996,
        17.35872,
        20.3776
      ]
    },
    {
      "id": 3264147693,
      "image_id": 4985379693,
      "category_id": 7871219693,
      "segmentation": [],
      "area": 388.17586216960007,
      "bbox": [
        55.09439999999999,
        481.88672,
        21.88672,
        17.735680000000002
      ]
    }
  ],
  "categories": [
    {
      "id": 7871219693,
      "name": "AppleBBCH81",
      "supercategory": "apple"
    }
  ]
}